art_studio_tz/__init__.py
art_studio_tz/__main__.py
art_studio_tz/api.py
art_studio_tz/cli.py
art_studio_tz/db.py
art_studio_tz/db_sql.py
art_studio_tz-0.1.1.dist-info/METADATA
art_studio_tz-0.1.1.dist-info/WHEEL
art_studio_tz-0.1.1.dist-info/entry_points.txt
art_studio_tz-0.1.1.dist-info/licenses/LICENSE
art_studio_tz-0.1.1.dist-info/RECORD
