Metadata-Version: 2.4
Name: art_studio_tz
Version: 0.1.1
Summary: Art studio tz CLI
License: MIT
License-File: LICENSE
Author: Ilin Maksim
Author-email: ilin1980maks@gmail.com
Requires-Python: >=3.10
Classifier: License :: OSI Approved :: MIT License
Classifier: Programming Language :: Python :: 3
Classifier: Programming Language :: Python :: 3.10
Classifier: Programming Language :: Python :: 3.11
Classifier: Programming Language :: Python :: 3.12
Classifier: Programming Language :: Python :: 3.13
Classifier: Programming Language :: Python :: 3.14
Provides-Extra: test
Requires-Dist: PyMySQL (==1.1.2)
Requires-Dist: Pygments (==2.19.2)
Requires-Dist: SQLAlchemy (==2.0.43)
Requires-Dist: certifi (==2025.8.3)
Requires-Dist: charset-normalizer (==3.4.3)
Requires-Dist: click (==8.3.0)
Requires-Dist: greenlet (==3.2.4)
Requires-Dist: idna (==3.10)
Requires-Dist: iniconfig (==2.1.0)
Requires-Dist: markdown-it-py (==4.0.0)
Requires-Dist: mdurl (==0.1.2)
Requires-Dist: packaging (==25.0)
Requires-Dist: pluggy (==1.6.0)
Requires-Dist: requests (==2.32.5)
Requires-Dist: rich (==14.1.0)
Requires-Dist: shellingham (==1.5.4)
Requires-Dist: typer (==0.19.2)
Requires-Dist: typing_extensions (==4.15.0)
Requires-Dist: urllib3 (==2.5.0)
Project-URL: Homepage, https://github.com/nafanius/art_studio_tz
